netcollector/__init__.py
netcollector/base_device.py
netcollector/collector.py
netcollector/utils.py
netcollector/modules/arista_device.py
netcollector/modules/cisco_device.py
netcollector/modules/cumulus_device.py
netcollector-0.1.0.dist-info/METADATA
netcollector-0.1.0.dist-info/WHEEL
netcollector-0.1.0.dist-info/top_level.txt
netcollector-0.1.0.dist-info/RECORD
