Metadata-Version: 2.4
Name: netcollector
Version: 0.1.0
Summary: Network data collector for networking platforms which collects data over SSH
Author-email: Naufal Jamal <naufalkj_2000@yahoo.co.in>
License: MIT
Classifier: Programming Language :: Python :: 3
Classifier: License :: OSI Approved :: MIT License
Classifier: Operating System :: OS Independent
Requires-Python: >=3.7
Requires-Dist: netmiko
